SklearnXuexiShouceChuyi/README.md
SklearnXuexiShouceChuyi/__init__.py
SklearnXuexiShouceChuyi/__main__.py
SklearnXuexiShouceChuyi/file.epub
SklearnXuexiShouceChuyi/index.html
SklearnXuexiShouceChuyi/css/__init__.py
SklearnXuexiShouceChuyi/css/annotations.css
SklearnXuexiShouceChuyi/css/main.css
SklearnXuexiShouceChuyi/css/normalize.css
SklearnXuexiShouceChuyi/css/popup.css
SklearnXuexiShouceChuyi/font/__init__.py
SklearnXuexiShouceChuyi/font/fontello.eot
SklearnXuexiShouceChuyi/font/fontello.svg
SklearnXuexiShouceChuyi/font/fontello.ttf
SklearnXuexiShouceChuyi/font/fontello.woff
SklearnXuexiShouceChuyi/img/__init__.py
SklearnXuexiShouceChuyi/img/annotator-glyph-sprite.png
SklearnXuexiShouceChuyi/img/annotator-icon-sprite.png
SklearnXuexiShouceChuyi/img/apple-touch-icon.png
SklearnXuexiShouceChuyi/img/cancelfullscreen.png
SklearnXuexiShouceChuyi/img/close.png
SklearnXuexiShouceChuyi/img/fullscreen.png
SklearnXuexiShouceChuyi/img/loader.gif
SklearnXuexiShouceChuyi/img/menu-icon.png
SklearnXuexiShouceChuyi/img/save.png
SklearnXuexiShouceChuyi/img/saved.png
SklearnXuexiShouceChuyi/img/settings-s.png
SklearnXuexiShouceChuyi/img/settings.png
SklearnXuexiShouceChuyi/img/star.png
SklearnXuexiShouceChuyi/js/__init__.py
SklearnXuexiShouceChuyi/js/epub.js
SklearnXuexiShouceChuyi/js/epub.min.js
SklearnXuexiShouceChuyi/js/epub.min.map
SklearnXuexiShouceChuyi/js/hooks.min.js
SklearnXuexiShouceChuyi/js/hooks.min.map
SklearnXuexiShouceChuyi/js/reader.js
SklearnXuexiShouceChuyi/js/reader.js.map
SklearnXuexiShouceChuyi/js/reader.min.js
SklearnXuexiShouceChuyi/js/reader.min.map
SklearnXuexiShouceChuyi/js/hooks/__init__.py
SklearnXuexiShouceChuyi/js/hooks/extensions/__init__.py
SklearnXuexiShouceChuyi/js/hooks/extensions/highlight.js
SklearnXuexiShouceChuyi/js/libs/__init__.py
SklearnXuexiShouceChuyi/js/libs/jquery.min.js
SklearnXuexiShouceChuyi/js/libs/localforage.min.js
SklearnXuexiShouceChuyi/js/libs/screenfull.js
SklearnXuexiShouceChuyi/js/libs/screenfull.min.js
sklearn_xuexi_shouce_chuyi-2024.3.5.0.dist-info/METADATA
sklearn_xuexi_shouce_chuyi-2024.3.5.0.dist-info/WHEEL
sklearn_xuexi_shouce_chuyi-2024.3.5.0.dist-info/entry_points.txt
sklearn_xuexi_shouce_chuyi-2024.3.5.0.dist-info/top_level.txt
sklearn_xuexi_shouce_chuyi-2024.3.5.0.dist-info/RECORD
